tradata_core_py-0.1.0.dist-info/licenses/LICENSE
tradata_logger/__init__.py
tradata_logger/config/__init__.py
tradata_logger/config/settings.py
tradata_logger/core/__init__.py
tradata_logger/core/engine.py
tradata_logger/core/formatter.py
tradata_logger/core/handler.py
tradata_logger/core/logger.py
tradata_logger/middleware/__init__.py
tradata_logger/middleware/fastapi.py
tradata_logger/middleware/flask.py
tradata_logger/utils/__init__.py
tradata_logger/utils/cache_helper.py
tradata_logger/utils/context.py
tradata_logger/utils/decorators.py
tradata_logger/utils/response_builder.py
tradata_core_py-0.1.0.dist-info/METADATA
tradata_core_py-0.1.0.dist-info/WHEEL
tradata_core_py-0.1.0.dist-info/top_level.txt
tradata_core_py-0.1.0.dist-info/RECORD
