Metadata-Version: 2.4
Name: tradata-core-py
Version: 0.1.0
Summary: Professional core framework for trading applications
Author-email: TradATA Team <team@tradata.com>
Maintainer-email: TradATA Team <team@tradata.com>
License: MIT
Project-URL: Homepage, https://github.com/TradataTech/tradata-core-py
Project-URL: Repository, https://github.com/TradataTech/tradata-core-py
Project-URL: Documentation, https://github.com/TradataTech/tradata-core-py/tree/main/docs
Project-URL: Changelog, https://github.com/TradataTech/tradata-core-py/blob/main/CHANGELOG.md
Project-URL: Issues, https://github.com/TradataTech/tradata-core-py/issues
Project-URL: Discussions, https://github.com/TradataTech/tradata-core-py/discussions
Keywords: core,logging,trading,fastapi,middleware,observability,framework
Classifier: Development Status :: 4 - Beta
Classifier: Intended Audience :: Developers
Classifier: Intended Audience :: Financial and Insurance Industry
Classifier: License :: OSI Approved :: MIT License
Classifier: Operating System :: OS Independent
Classifier: Programming Language :: Python :: 3
Classifier: Programming Language :: Python :: 3.8
Classifier: Programming Language :: Python :: 3.9
Classifier: Programming Language :: Python :: 3.10
Classifier: Programming Language :: Python :: 3.11
Classifier: Programming Language :: Python :: 3.12
Classifier: Topic :: Software Development :: Libraries :: Python Modules
Classifier: Topic :: System :: Logging
Classifier: Topic :: Office/Business :: Financial :: Investment
Requires-Python: >=3.8
License-File: LICENSE
Requires-Dist: fastapi>=0.68.0
Requires-Dist: starlette>=0.14.0
Requires-Dist: pydantic>=1.8.0
Requires-Dist: python-json-logger>=2.0.0
Provides-Extra: dev
Requires-Dist: pytest>=7.0.0; extra == "dev"
Requires-Dist: pytest-cov>=4.0.0; extra == "dev"
Requires-Dist: pytest-asyncio>=0.21.0; extra == "dev"
Requires-Dist: black>=22.0.0; extra == "dev"
Requires-Dist: flake8>=5.0.0; extra == "dev"
Requires-Dist: mypy>=1.0.0; extra == "dev"
Requires-Dist: httpx>=0.24.0; extra == "dev"
Provides-Extra: test
Requires-Dist: pytest>=7.0.0; extra == "test"
Requires-Dist: pytest-cov>=4.0.0; extra == "test"
Requires-Dist: pytest-asyncio>=0.21.0; extra == "test"
Requires-Dist: httpx>=0.24.0; extra == "test"
Provides-Extra: docs
Requires-Dist: sphinx>=5.0.0; extra == "docs"
Requires-Dist: sphinx-rtd-theme>=1.0.0; extra == "docs"
Requires-Dist: myst-parser>=0.18.0; extra == "docs"
Dynamic: license-file
